{
    "id": 118,
    "field_of_knowledge": "Дифференциальные уравнения и динамические системы",
    "short_name": "StrStab",
    "full_name": "Структурная устойчивость",
    "size": "семинар (s)",
    "description": "https://drive.google.com/file/d/1pv7u_cWtzaHZNlrl00kVs7-v0VqzM0QE/view?usp=sharing",
    "direction": "М3–4, НоД3–4",
    "lecturer_id": 34,
    "year": "2023",
    "context": {
        "динамические системы": "динамические системы",
        "структура": "структура",
        "устойчивость": "устойчивость",
        "анализ": "анализ",
        "матрицы": "матрицы",
        "параметры": "параметры",
        "моделирование": "моделирование",
        "гладкие функции": "гладкие функции",
        "теория графов": "теория графов",
        "линеаризация": "линеаризация",
        "матричные вычисления": "матричные вычисления",
        "теорема Ляпунова": "теорема Ляпунова",
        "стабильность": "стабильность",
        "нелинейность": "нелинейность",
        "функциональный анализ": "функциональный анализ",
        "вариационное исчисление": "вариационное исчисление",
        "градиентный метод": "градиентный метод",
        "спектральная теория": "спектральная теория",
        "численные методы": "численные методы",
        "оптимизация": "оптимизация",
        "управление": "управление",
        "теория управления": "теория управления",
        "теория оптимального управления": "теория оптимального управления",
        "частично линейные системы": "частично линейные системы",
        "системы дифференциальных уравнений": "системы дифференциальных уравнений",
        "термодинамика": "термодинамика",
        "метод множителей Лагранжа": "метод множителей Лагранжа",
        "векторные поля": "векторные поля",
        "гомологическая теория": "гомологическая теория",
        "оценка погрешности": "оценка погрешности"
    }
}