{
    "id": 213,
    "field_of_knowledge": "Программирование",
    "short_name": "BioinfAlgs",
    "full_name": "Алгоритмы биоинформатики",
    "size": "большой (2)",
    "description": "https://spbu-math-cs.github.io/choice2122/abstracts/BioinfAlgs.pdf",
    "direction": "СП4",
    "lecturer_id": 77,
    "year": "2023",
    "context": {
        "биоинформатика": "биоинформатика",
        "алгоритмы": "алгоритмы",
        "компьютерная биология": "компьютерная биология",
        "строковые алгоритмы": "строковые алгоритмы",
        "комбинаторные алгоритмы": "комбинаторные алгоритмы",
        "поиск генов": "поиск генов",
        "поиск мотивов": "поиск мотивов",
        "графовые алгоритмы": "графовые алгоритмы",
        "геномная сборка": "геномная сборка",
        "сравнительная геномика": "сравнительная геномика",
        "кластерный анализ": "кластерный анализ",
        "анализ экспрессии генов": "анализ экспрессии генов",
        "реконструкция эволюционных деревьев": "реконструкция эволюционных деревьев",
        "теоретический фон": "теоретический фон",
        "практические задачи": "практические задачи",
        "программирование": "программирование",
        "онлайн-курс": "онлайн-курс",
        "обучение с заранее доступными материалами": "обучение с заранее доступными материалами",
        "обсуждения": "обсуждения",
        "английский язык": "английский язык",
        "информационные технологии": "информационные технологии",
        "наука": "наука",
        "исследования": "исследования",
        "класс в формате 'flipped classroom'": "класс в формате 'flipped classroom'",
        "ломаный английский": "ломаный английский",
        "биологические последовательности": "биологические последовательности",
        "биоинформационные системы": "биоинформационные системы",
        "обработка данных": "обработка данных",
        "анализ данных": "анализ данных"
    }
}