{
    "id": 15,
    "field_of_knowledge": "Алгебра",
    "short_name": "AlgGeom2",
    "full_name": "Основы алгебраической геометрии (часть 2)",
    "size": "большой (2)",
    "description": "https://drive.google.com/open?id=1PSLYckrNEUbuGRGNZfmhOKfsfXH-Mtf6",
    "direction": "М4, НоД4, СМ2",
    "lecturer_id": 6,
    "year": "2023",
    "context": {
        "алгебраическая геометрия": "алгебраическая геометрия",
        "эллиптические кривые": "эллиптические кривые",
        "дивизоры": "дивизоры",
        "нормирование": "нормирование",
        "ложные точки": "ложные точки",
        "дифференциальные формы": "дифференциальные формы",
        "род кривой": "род кривой",
        "теорема Римана-Роха": "теорема Римана-Роха",
        "абелева группа": "абелева группа",
        "группа классов дивизоров": "группа классов дивизоров",
        "кольца дискретного нормирования": "кольца дискретного нормирования",
        "регулярность": "регулярность",
        "гиперповерхности": "гиперповерхности",
        "индекс пересечения": "индекс пересечения",
        "теорема Безу": "теорема Безу",
        "размерность алгебры": "размерность алгебры"
    }
}